README.rst
setup.py
dirus/__init__.py
dirus/classes.py
dirus/cmd.py
dirus/constants.py
dirus.egg-info/PKG-INFO
dirus.egg-info/SOURCES.txt
dirus.egg-info/dependency_links.txt
dirus.egg-info/entry_points.txt
dirus.egg-info/not-zip-safe
dirus.egg-info/pbr.json
dirus.egg-info/requires.txt
dirus.egg-info/top_level.txt