Metadata-Version: 1.0
Name: dirus
Version: 1.0.0
Summary: Dirus
Home-page: http://github.com/ampledata/dirus
Author: Greg Albrecht
Author-email: oss@undef.net
License: Copyright 2016 Orion Labs, Inc.
